zappy/__init__.py
zappy/zappy.py
zappy_sync-0.6.0.dist-info/LICENSE
zappy_sync-0.6.0.dist-info/METADATA
zappy_sync-0.6.0.dist-info/WHEEL
zappy_sync-0.6.0.dist-info/entry_points.txt
zappy_sync-0.6.0.dist-info/RECORD
