Metadata-Version: 2.1
Name: zappy-sync
Version: 0.6.0
Summary: Little utility to rsync local zappy files to cloud storage
Home-page: https://github.com/radoshi/zappy-sync
License: MIT
Author: Rushabh Doshi
Author-email: radoshi+pypi@gmail.com
Requires-Python: >=3.11,<4.0
Classifier: License :: OSI Approved :: MIT License
Classifier: Programming Language :: Python :: 3
Classifier: Programming Language :: Python :: 3.11
Requires-Dist: click (>=8.1.7,<9.0.0)
Requires-Dist: google-cloud-storage (>=2.11.0,<3.0.0)
Requires-Dist: rich (>=13.5.3,<14.0.0)
Requires-Dist: tomli (>=2.0.1,<3.0.0)
Requires-Dist: watchdog (>=3.0.0,<4.0.0)
Project-URL: Repository, https://github.com/radoshi/zappy-sync
